virus_scanner/__init__.py
virus_scanner/vscan_config.py
virus_scanner/Main/main.py
virus_scanner/Meta_Defender/MetaDefenderMain.py
virus_scanner/VirusTotal_API/VirusTotal_API_File.py
virus_scanner/VirusTotal_API/VirusTotal_API_URL.py
vscan-1.0.data/scripts/vscan
vscan-1.0.dist-info/LICENSE
vscan-1.0.dist-info/METADATA
vscan-1.0.dist-info/WHEEL
vscan-1.0.dist-info/top_level.txt
vscan-1.0.dist-info/RECORD
