Metadata-Version: 2.1
Name: vscan
Version: 1.0
Summary: A cli tool that uses APIs to scan malicious files & urls
Home-page: https://github.com/HWTechClub/Virus-Scanner
Author: HWU Sec Team
Author-email: pranavc10@hotmail.com
License: UNKNOWN
Platform: UNKNOWN
Classifier: Programming Language :: Python :: 3
Classifier: License :: OSI Approved :: GNU General Public License v2 (GPLv2)
Classifier: Operating System :: OS Independent
Requires-Dist: PyInquirer
Requires-Dist: pyfiglet
Requires-Dist: pypi-cli
Requires-Dist: pyyaml
Requires-Dist: tkintertable
